<?xml version='1.0' encoding='UTF-8'?>
<organe xmlns="http://schemas.assemblee-nationale.fr/referentiel" xmlns:xsi="http://www.w3.org/2001/XMLSchema-instance" xsi:type="OrganeExtraParlementaire_type">
  <uid>PO679161</uid>
  <codeType>ORGEXTPARL</codeType>
  <libelle>Commission nationale des bourses de l'Agence pour l'enseignement français à l'étranger</libelle>
  <libelleEdition>de la Commission nationale des bourses de l'Agence pour l'enseignement français à l'étranger</libelleEdition>
  <libelleAbrege>Commission nationale des bourses</libelleAbrege>
  <libelleAbrev>121</libelleAbrev>
  <viMoDe>
    <dateDebut>2012-10-05</dateDebut>
    <dateAgrement xsi:nil="true"/>
    <dateFin xsi:nil="true"/>
  </viMoDe>
  <organeParent xsi:nil="true"/>
  <chambre xsi:nil="true"/>
  <regime>5ème République</regime>
  <legislature xsi:nil="true"/>
  <regimeJuridique>Article D. 531-50 du code de l'éducation</regimeJuridique>
  <siteInternet>http://www.aefe.fr/aefe/organigramme/organigramme-de-laefe-commission-nationale-des-bourses-cnb</siteInternet>
  <nombreReunionsAnnuelles xsi:nil="true"/>
</organe>
